picketapi/__init__.py
picketapi/exceptions.py
picketapi/helpers.py
picketapi/picket.py
picketapi/types.py
picketapi-0.1.1.dist-info/WHEEL
picketapi-0.1.1.dist-info/METADATA
picketapi-0.1.1.dist-info/RECORD
