Metadata-Version: 2.1
Name: picketapi
Version: 0.1.1
Summary: The official Python library for the Picket API (https://picketapi.com/)
Home-page: https://github.com/picketapi/picket-python
Author: Devin Stein
Author-email: devstein@seas.upenn.edu
Requires-Python: >=3.7,<4.0
Classifier: Programming Language :: Python :: 3
Classifier: Programming Language :: Python :: 3.7
Classifier: Programming Language :: Python :: 3.8
Classifier: Programming Language :: Python :: 3.9
Classifier: Programming Language :: Python :: 3.10
Classifier: Programming Language :: Python :: 3.11
Requires-Dist: requests (>=2.28.1,<3.0.0)
